genice2_yaplot/__init__.py
genice2_yaplot/formats/__init__.py
genice2_yaplot/formats/yaplot.py
genice2_yaplot-0.2.dist-info/LICENSE
genice2_yaplot-0.2.dist-info/METADATA
genice2_yaplot-0.2.dist-info/WHEEL
genice2_yaplot-0.2.dist-info/entry_points.txt
genice2_yaplot-0.2.dist-info/RECORD
