Metadata-Version: 2.1
Name: genice2-yaplot
Version: 0.2
Summary: yaplot format plugin for GenIce2.
License: MIT
Author: vitroid
Author-email: vitroid@gmail.com
Requires-Python: >=3.9,<4.0
Classifier: License :: OSI Approved :: MIT License
Classifier: Programming Language :: Python :: 3
Classifier: Programming Language :: Python :: 3.9
Classifier: Programming Language :: Python :: 3.10
Classifier: Programming Language :: Python :: 3.11
Classifier: Programming Language :: Python :: 3.12
Requires-Dist: GenIce2 (>=2)
Requires-Dist: numpy (>=1.26.4,<2.0.0)
Requires-Dist: yaplotlib
